docs/conf.py
simple_salesforce/__init__.py
simple_salesforce/api.py
simple_salesforce/bulk.py
simple_salesforce/bulk2.py
simple_salesforce/exceptions.py
simple_salesforce/format.py
simple_salesforce/login.py
simple_salesforce/messages.py
simple_salesforce/metadata.py
simple_salesforce/metadata.wsdl
simple_salesforce/util.py
simple_salesforce/aio/__init__.py
simple_salesforce/aio/aio_util.py
simple_salesforce/aio/api.py
simple_salesforce/aio/bulk.py
simple_salesforce/aio/bulk2.py
simple_salesforce/aio/login.py
simple_salesforce/aio/metadata.py
tests/__init__.py
tests/test_api.py
tests/test_bulk.py
tests/test_bulk2.py
tests/test_format.py
tests/test_login.py
tests/test_util.py
tests/test_aio/conftest.py
tests/test_aio/test_aio_util.py
tests/test_aio/test_api.py
tests/test_aio/test_bulk.py
tests/test_aio/test_bulk2.py
tests/test_aio/test_login.py
tests/test_aio/test_metadata.py
async_simple_salesforce-1.12.6a4.dist-info/LICENSE.txt
async_simple_salesforce-1.12.6a4.dist-info/METADATA
async_simple_salesforce-1.12.6a4.dist-info/WHEEL
async_simple_salesforce-1.12.6a4.dist-info/top_level.txt
async_simple_salesforce-1.12.6a4.dist-info/RECORD
