Metadata-Version: 2.1
Name: async-simple-salesforce
Version: 1.12.6a4
Summary: Async fork of simple-salesforce
Author-email: Erik Aker <eaker@mulliganfunding.com>
License: Copyright 2012 New Organizing Institute Education Fund
Project-URL: Repository, https://github.com/MulliganFunding/async-simple-salesforce
Project-URL: Documentation, https://github.com/MulliganFunding/async-simple-salesforce/blob/main/README.md
Project-URL: Changelog, https://github.com/MulliganFunding/async-simple-salesforce/blob/main/CHANGELOG.md
Project-URL: Releases, https://github.com/MulliganFunding/async-simple-salesforce/releases
Keywords: uv,requirements,packaging
Classifier: Development Status :: 3 - Alpha
Classifier: License :: OSI Approved :: Apache Software License
Classifier: Intended Audience :: Developers
Classifier: Intended Audience :: System Administrators
Classifier: Operating System :: OS Independent
Classifier: Topic :: Internet :: WWW/HTTP
Classifier: Programming Language :: Python
Classifier: Programming Language :: Python :: 3.10
Classifier: Programming Language :: Python :: 3.11
Classifier: Programming Language :: Python :: 3.12
Requires-Python: >=3.10
License-File: LICENSE.txt
Requires-Dist: aiofiles >=24.1.0
Requires-Dist: httpx >=0.18.2
Requires-Dist: more-itertools >=8.10.0
Requires-Dist: pendulum
Requires-Dist: pyjwt[crypto]
Requires-Dist: requests >=2.26.0
Requires-Dist: typing-extensions
Requires-Dist: zeep
